LICENSE
README.md
setup.cfg
setup.py
namedredis.egg-info/PKG-INFO
namedredis.egg-info/SOURCES.txt
namedredis.egg-info/dependency_links.txt
namedredis.egg-info/requires.txt
namedredis.egg-info/top_level.txt
namedredis.egg-info/zip-safe
nredis/__init__.py
nredis/__main__.py