Metadata-Version: 2.1
Name: namedredis
Version: 1.0.0
Summary: A library to make sharing the same redis connection easier
Home-page: UNKNOWN
Author: Chris Nasr - Ouroboros Coding Inc.
Author-email: chris@ouroboroscoding.com
License: MIT
Project-URL: Source, https://github.com/ouroboroscoding/namedredis
Project-URL: Tracker, https://github.com/ouroboroscoding/namedredis/issues
Keywords: redis,config
Platform: UNKNOWN
Requires-Python: >=3.10
License-File: LICENSE
